rdiffweb/__init__.py
rdiffweb/main.py
rdiffweb/rdw_app.py
rdiffweb/test.py
rdiffweb/controller/__init__.py
rdiffweb/controller/api.py
rdiffweb/controller/api_currentuser.py
rdiffweb/controller/api_openapi.py
rdiffweb/controller/dispatch.py
rdiffweb/controller/filter_authorization.py
rdiffweb/controller/form.py
rdiffweb/controller/formdb.py
rdiffweb/controller/page_admin.py
rdiffweb/controller/page_admin_activity.py
rdiffweb/controller/page_admin_logs.py
rdiffweb/controller/page_admin_repos.py
rdiffweb/controller/page_admin_session.py
rdiffweb/controller/page_admin_sysinfo.py
rdiffweb/controller/page_admin_users.py
rdiffweb/controller/page_browse.py
rdiffweb/controller/page_delete.py
rdiffweb/controller/page_graphs.py
rdiffweb/controller/page_history.py
rdiffweb/controller/page_locations.py
rdiffweb/controller/page_login.py
rdiffweb/controller/page_logs.py
rdiffweb/controller/page_mfa.py
rdiffweb/controller/page_pref_general.py
rdiffweb/controller/page_pref_mfa.py
rdiffweb/controller/page_pref_notification.py
rdiffweb/controller/page_pref_session.py
rdiffweb/controller/page_pref_sshkeys.py
rdiffweb/controller/page_pref_tokens.py
rdiffweb/controller/page_prefs.py
rdiffweb/controller/page_restore.py
rdiffweb/controller/page_settings.py
rdiffweb/controller/page_stats.py
rdiffweb/controller/page_status.py
rdiffweb/controller/tests/__init__.py
rdiffweb/controller/tests/test_api.py
rdiffweb/controller/tests/test_check_links.py
rdiffweb/controller/tests/test_controller.py
rdiffweb/controller/tests/test_openapi.py
rdiffweb/controller/tests/test_page_admin.py
rdiffweb/controller/tests/test_page_admin_activity.py
rdiffweb/controller/tests/test_page_admin_logs.py
rdiffweb/controller/tests/test_page_admin_repos.py
rdiffweb/controller/tests/test_page_admin_session.py
rdiffweb/controller/tests/test_page_admin_sysinfo.py
rdiffweb/controller/tests/test_page_admin_users.py
rdiffweb/controller/tests/test_page_browse.py
rdiffweb/controller/tests/test_page_delete.py
rdiffweb-2.11.0.dist-info/licenses/LICENSE
rdiffweb-2.11.0.dist-info/METADATA
rdiffweb-2.11.0.dist-info/WHEEL
rdiffweb-2.11.0.dist-info/entry_points.txt
rdiffweb-2.11.0.dist-info/top_level.txt
rdiffweb-2.11.0.dist-info/RECORD
