Metadata-Version: 2.4
Name: rdiffweb
Version: 2.11.0
Summary: A web interface to rdiff-backup repositories.
Author-email: Patrik Dufresne <patrik@ikus-soft.com>
License:                     GNU GENERAL PUBLIC LICENSE
Project-URL: Homepage, https://rdiffweb.org
Project-URL: documentation, https://www.ikus-soft.com/archive/rdiffweb/doc/latest/html/
Project-URL: source, https://gitlab.com/ikus-soft/rdiffweb
Project-URL: bug_tracker, https://gitlab.com/ikus-soft/rdiffweb/-/issues
Classifier: Development Status :: 5 - Production/Stable
Classifier: Intended Audience :: System Administrators
Classifier: Programming Language :: Python :: 3
Classifier: Programming Language :: Python :: 3.6
Classifier: Programming Language :: Python :: 3.7
Classifier: Programming Language :: Python :: 3.8
Classifier: Programming Language :: Python :: 3.9
Classifier: Programming Language :: Python :: 3.10
Classifier: Framework :: CherryPy
Requires-Python: <4,>=3.8
License-File: LICENSE
Requires-Dist: apscheduler
Requires-Dist: argon2-cffi>=18.3.0
Requires-Dist: babel>=0.9.6
Requires-Dist: cached-property
Requires-Dist: CherryPy>=18
Requires-Dist: cheroot<11
Requires-Dist: configargparse
Requires-Dist: distro
Requires-Dist: humanfriendly
Requires-Dist: Jinja2>=2.10
Requires-Dist: ldap3
Requires-Dist: MarkupSafe<3
Requires-Dist: packaging
Requires-Dist: psutil>=2.1.1
Requires-Dist: pytz
Requires-Dist: requests
Requires-Dist: requests_oauthlib
Requires-Dist: sqlalchemy<3,>=1.4
Requires-Dist: WTForms<4,>=2.2
Requires-Dist: zxcvbn>=4.4.27
Provides-Extra: test
Requires-Dist: html5lib; extra == "test"
Requires-Dist: pytest; extra == "test"
Requires-Dist: parameterized; extra == "test"
Requires-Dist: responses; extra == "test"
Requires-Dist: selenium; extra == "test"
Dynamic: license-file
